gada_compose/__init__.py
gada_compose/__main__.py
gada_compose/__version__.py
gada_compose/main.py
gada_compose/parser.py
gada_compose/program.py
gada_compose/step.py
gada_compose/test_utils.py
test/__init__.py
test/gadalang_testnodes/__init__.py
gada_compose-0.1a0.dist-info/LICENSE
gada_compose-0.1a0.dist-info/METADATA
gada_compose-0.1a0.dist-info/WHEEL
gada_compose-0.1a0.dist-info/entry_points.txt
gada_compose-0.1a0.dist-info/top_level.txt
gada_compose-0.1a0.dist-info/RECORD
