Metadata-Version: 2.1
Name: gada-compose
Version: 0.1a0
Summary: Python frontend for mysql cli
Home-page: https://github.com/gadalang/gada-compose
Author: Jeremy Morosi
Author-email: jeremymorosi@hotmail.com
License: UNKNOWN
Project-URL: Bug Tracker, https://github.com/gadalang/gada-compose/issues
Project-URL: Source Code, https://github.com/gadalang/gada-compose/
Platform: UNKNOWN
Classifier: Development Status :: 3 - Alpha
Classifier: Intended Audience :: Developers
Classifier: Topic :: Software Development :: Build Tools
Classifier: Programming Language :: Python :: 3.7
Classifier: Programming Language :: Python :: 3.8
Classifier: Programming Language :: Python :: 3.9
Requires-Python: >=3.7
Requires-Dist: pygada-runtime
